<?xml version="1.0" encoding="UTF-8" standalone="yes"?>

<channels>
  <channels_info> <!-- this is opitonal -->
  <title>[COLOR lime]•[/COLOR]    [COLOR lightyellow][B]Seriale[/B] [/COLOR]</title> 
  <thumbnail>https://upload.wikimedia.org/wikipedia/en/5/54/The_Serial_Logo.png</thumbnail>
  <fanart>http://filmowo.net/wp-content/uploads/2017/07/wspolczesneseriale.jpg</fanart>
  </channels_info>
<!-----------------------------------------------------------------END------------------------------------------------------------------------------------>
<!-----------------------------------------------------------------END------------------------------------------------------------------------------------>	
	<channel>
      <name>[COLOR lime]•[/COLOR]    [COLOR lightyellow][B]Battlestar Galactica (2004-2009) Sezon 1 [/B][/COLOR]</name>
      <thumbnail>https://upload.wikimedia.org/wikipedia/en/c/c6/BSG_Season_1_DVD.jpg</thumbnail>
      <fanart>https://www.walldevil.com/wallpapers/a46/battlestar-galactica-last-supper.jpg</fanart>
<!-----------------------------------------------------------------END------------------------------------------------------------------------------------>	
<!-----------------------------------------------------------------END------------------------------------------------------------------------------------>	
        <subchannel>
          <name>[COLOR lime]•[/COLOR]    [COLOR yellow][B][s01e00][/B][/COLOR]     [COLOR lightyellow][B]Pilot[/B][/COLOR]</name>
          <thumbnail>https://upload.wikimedia.org/wikipedia/en/c/c6/BSG_Season_1_DVD.jpg</thumbnail>
          <fanart>https://www.walldevil.com/wallpapers/a46/battlestar-galactica-last-supper.jpg</fanart>
            <subitems>
				<subitem>
                  <title>[COLOR green][B]480p[/B][/COLOR] [COLOR lightyellow][B]  openload.co[/B][/COLOR]</title>
			      <thumbnail>https://openload.co/assets/img/logo.png</thumbnail>
                  <urlsolve>https://openload.co/embed/Qx6U63pwRXk</urlsolve>	
				</subitem>
				
				<subitem>
                  <title>[COLOR green][B]480p[/B][/COLOR] [COLOR lightyellow][B]  openload.co[/B][/COLOR]</title>
			      <thumbnail>https://openload.co/assets/img/logo.png</thumbnail>
                  <urlsolve>https://openload.co/embed/SmzmRZXWI1M</urlsolve>	
				</subitem>
				
				<subitem>
                  <title>[COLOR green][B]480p[/B][/COLOR] [COLOR lightyellow][B]  openload.co[/B][/COLOR]</title>
			      <thumbnail>https://openload.co/assets/img/logo.png</thumbnail>
                  <urlsolve>https://openload.co/embed/OWbOnPl26Z8</urlsolve>	
				</subitem>
				
				<subitem>
                  <title>[COLOR green][B]480p[/B][/COLOR] [COLOR lightyellow][B]  openload.co[/B][/COLOR]</title>
			      <thumbnail>https://openload.co/assets/img/logo.png</thumbnail>
                  <urlsolve>https://openload.co/embed/t0EIrz2oKFk</urlsolve>	
				</subitem>
				
			    <subitem>
                  <title>[COLOR green][B]480p[/B][/COLOR] [COLOR lightyellow][B]  streamango.com[/B][/COLOR]</title>
			      <thumbnail>https://streamango.com/assets/img/feature-icon3.png</thumbnail>
                  <urlsolve>https://streamango.com/embed/klnctmdleanalbmt</urlsolve>	
				</subitem> 
				
				<subitem>
                  <title>[COLOR green][B]480p[/B][/COLOR] [COLOR lightyellow][B]  streamango.com[/B][/COLOR]</title>
			      <thumbnail>https://streamango.com/assets/img/feature-icon3.png</thumbnail>
                  <urlsolve>https://streamango.com/embed/qlmokotpnaeassds</urlsolve>	
				</subitem> 
				
				<subitem>
                  <title>[COLOR green][B]480p[/B][/COLOR] [COLOR lightyellow][B]  streamango.com[/B][/COLOR]</title>
			      <thumbnail>https://streamango.com/assets/img/feature-icon3.png</thumbnail>
                  <urlsolve>https://streamango.com/embed/sqdrcebdcnosedar</urlsolve>	
				</subitem>
				
				<subitem>
                  <title>[COLOR green][B]480p[/B][/COLOR] [COLOR lightyellow][B]  streamango.com[/B][/COLOR]</title>
			      <thumbnail>https://streamango.com/assets/img/feature-icon3.png</thumbnail>
                  <urlsolve>http://streamango.com/embed/aafqmfprlnpaalqb</urlsolve>	
				</subitem>
				
				<subitem>
                  <title>[COLOR green][B]480p[/B][/COLOR] [COLOR lightyellow][B]  streamcherry.com[/B][/COLOR]</title>
			      <thumbnail>http://streamcherry.com/assets/img/logo.png</thumbnail>
                  <urlsolve>http://streamcherry.com/embed/cpomnlfncattacqm</urlsolve>	
				</subitem>
				
				<subitem>
                  <title>[COLOR green][B]480p[/B][/COLOR] [COLOR lightyellow][B]  streamcherry.com[/B][/COLOR]</title>
			      <thumbnail>http://streamcherry.com/assets/img/logo.png</thumbnail>
                  <urlsolve>http://streamcherry.com/embed/ratqotefkftnfnpq</urlsolve>	
				</subitem>
				
				<subitem>
                  <title>[COLOR green][B]480p[/B][/COLOR] [COLOR lightyellow][B]  streamcherry.com[/B][/COLOR]</title>
			      <thumbnail>http://streamcherry.com/assets/img/logo.png</thumbnail>
                  <urlsolve>http://streamcherry.com/embed/orsbcpoedmndocfq</urlsolve>	
				</subitem>
				
				<subitem>
                  <title>[COLOR green][B]480p[/B][/COLOR] [COLOR lightyellow][B]  streamcherry.com[/B][/COLOR]</title>
			      <thumbnail>http://streamcherry.com/assets/img/logo.png</thumbnail>
                  <urlsolve>http://streamcherry.com/embed/cestdlkbqpeqnpcm</urlsolve>	
				</subitem>
				
				<subitem>
                  <title>[COLOR green][B]480p[/B][/COLOR] [COLOR lightyellow][B]  vidoza.net[/B][/COLOR]</title>
			      <thumbnail>https://netbusinessrating.com/inc/imghttps.php?url=aHR0cHM6Ly9uZXRidXNpbmVzc3JhdGluZy5jb20vaW1nL3VwbG9hZGVkL3RodW1iL3RodW1iXzQyMDk1X3ZpZG96YV8xNzA3MzAwODUyNTkucG5n</thumbnail>
                  <urlsolve>http://vidoza.net/embed-pwg9mxs1idb1.html</urlsolve>	
				</subitem>
				
				<subitem>
                  <title>[COLOR green][B]480p[/B][/COLOR] [COLOR lightyellow][B]  vidoza.net[/B][/COLOR]</title>
			      <thumbnail>https://netbusinessrating.com/inc/imghttps.php?url=aHR0cHM6Ly9uZXRidXNpbmVzc3JhdGluZy5jb20vaW1nL3VwbG9hZGVkL3RodW1iL3RodW1iXzQyMDk1X3ZpZG96YV8xNzA3MzAwODUyNTkucG5n</thumbnail>
                  <urlsolve>https://vidoza.net/embed-eaysxe4q2zsz.html</urlsolve>	
				</subitem>
				
				<subitem>
                  <title>[COLOR green][B]480p[/B][/COLOR] [COLOR lightyellow][B]  vidoza.net[/B][/COLOR]</title>
			      <thumbnail>https://netbusinessrating.com/inc/imghttps.php?url=aHR0cHM6Ly9uZXRidXNpbmVzc3JhdGluZy5jb20vaW1nL3VwbG9hZGVkL3RodW1iL3RodW1iXzQyMDk1X3ZpZG96YV8xNzA3MzAwODUyNTkucG5n</thumbnail>
                  <urlsolve>https://vidoza.net/embed-3jy9zgq7rm9p.html</urlsolve>	
				</subitem>
				
				<subitem>
                  <title>[COLOR green][B]480p[/B][/COLOR] [COLOR lightyellow][B]  vidoza.net[/B][/COLOR]</title>
			      <thumbnail>https://netbusinessrating.com/inc/imghttps.php?url=aHR0cHM6Ly9uZXRidXNpbmVzc3JhdGluZy5jb20vaW1nL3VwbG9hZGVkL3RodW1iL3RodW1iXzQyMDk1X3ZpZG96YV8xNzA3MzAwODUyNTkucG5n</thumbnail>
                  <urlsolve>https://vidoza.net/embed-60xq7grug63c.html</urlsolve>	
				</subitem>
				
				<subitem>
                  <title>[COLOR green][B]480p[/B][/COLOR] [COLOR lightyellow][B]  vidto.me[/B][/COLOR]</title>
			      <thumbnail>http://static.vidto.me/static/images/header-logo.png</thumbnail>
                  <urlsolve>http://vidto.me/embed-7z9xadr8e50z-693x495.html</urlsolve>	
				</subitem>
			</subitems>
		</subchannel>
<!-----------------------------------------------------------------END------------------------------------------------------------------------------------>	
        <subchannel>
          <name>[COLOR lime]•[/COLOR]    [COLOR yellow][B][s01e01][/B][/COLOR]     [COLOR lightyellow][B] 33[/B][/COLOR]</name>
          <thumbnail>https://upload.wikimedia.org/wikipedia/en/c/c6/BSG_Season_1_DVD.jpg</thumbnail>
          <fanart>https://www.walldevil.com/wallpapers/a46/battlestar-galactica-last-supper.jpg</fanart>
            <subitems>
				<subitem>
                  <title>[COLOR green][B]480p[/B][/COLOR] [COLOR lightyellow][B]  openload.co[/B][/COLOR]</title>
			      <thumbnail>https://openload.co/assets/img/logo.png</thumbnail>
                  <urlsolve>https://openload.co/embed/EH9Q_f7g7UA</urlsolve>	
				</subitem>
				
				<subitem>
                  <title>[COLOR green][B]480p[/B][/COLOR] [COLOR lightyellow][B]  openload.co[/B][/COLOR]</title>
			      <thumbnail>https://openload.co/assets/img/logo.png</thumbnail>
                  <urlsolve>https://openload.co/embed/FLa1KXN-skY</urlsolve>	
				</subitem>
				
				<subitem>
                  <title>[COLOR green][B]480p[/B][/COLOR] [COLOR lightyellow][B]  openload.co[/B][/COLOR]</title>
			      <thumbnail>https://openload.co/assets/img/logo.png</thumbnail>
                  <urlsolve>https://openload.co/embed/wmAMdMwXY5w</urlsolve>	
				</subitem>
				
				<subitem>
                  <title>[COLOR green][B]480p[/B][/COLOR] [COLOR lightyellow][B]  openload.co[/B][/COLOR]</title>
			      <thumbnail>https://openload.co/assets/img/logo.png</thumbnail>
                  <urlsolve>https://openload.co/embed/-YydlRnWHFI</urlsolve>	
				</subitem>
				
				<subitem>
                  <title>[COLOR green][B]480p[/B][/COLOR] [COLOR lightyellow][B]  streamango.com[/B][/COLOR]</title>
			      <thumbnail>https://streamango.com/assets/img/feature-icon3.png</thumbnail>
                  <urlsolve>http://streamango.com/embed/dksmoebsfpsemamc</urlsolve>	
				</subitem>
				
				<subitem>
                  <title>[COLOR green][B]480p[/B][/COLOR] [COLOR lightyellow][B]  streamango.com[/B][/COLOR]</title>
			      <thumbnail>https://streamango.com/assets/img/feature-icon3.png</thumbnail>
                  <urlsolve>http://streamango.com/embed/remntnalnloenpon</urlsolve>	
				</subitem>
				
				<subitem>
                  <title>[COLOR green][B]480p[/B][/COLOR] [COLOR lightyellow][B]  streamango.com[/B][/COLOR]</title>
			      <thumbnail>https://streamango.com/assets/img/feature-icon3.png</thumbnail>
                  <urlsolve>http://streamango.com/embed/ttnscdcnobsspekb</urlsolve>	
				</subitem>
				
				<subitem>
                  <title>[COLOR green][B]480p[/B][/COLOR] [COLOR lightyellow][B]  streamango.com[/B][/COLOR]</title>
			      <thumbnail>https://streamango.com/assets/img/feature-icon3.png</thumbnail>
                  <urlsolve>http://streamango.com/embed/qkebmffabtfbqfps</urlsolve>	
				</subitem>
				
				<subitem>
                  <title>[COLOR green][B]480p[/B][/COLOR] [COLOR lightyellow][B]  streamcherry.com[/B][/COLOR]</title>
			      <thumbnail>http://streamcherry.com/assets/img/logo.png</thumbnail>
                  <urlsolve>https://streamcherry.com/embed/dacemmcmmprssrat</urlsolve>	
				</subitem>
				
				<subitem>
                  <title>[COLOR green][B]480p[/B][/COLOR] [COLOR lightyellow][B]  streamcherry.com[/B][/COLOR]</title>
			      <thumbnail>http://streamcherry.com/assets/img/logo.png</thumbnail>
                  <urlsolve>http://streamcherry.com/embed/nlcctobplarlpare</urlsolve>	
				</subitem>
				
				<subitem>
                  <title>[COLOR green][B]480p[/B][/COLOR] [COLOR lightyellow][B]  streamcherry.com[/B][/COLOR]</title>
			      <thumbnail>http://streamcherry.com/assets/img/logo.png</thumbnail>
                  <urlsolve>https://streamcherry.com/embed/ttkfeckatctdmtot</urlsolve>	
				</subitem>
				
				<subitem>
                  <title>[COLOR green][B]480p[/B][/COLOR] [COLOR lightyellow][B]  streamcherry.com[/B][/COLOR]</title>
			      <thumbnail>http://streamcherry.com/assets/img/logo.png</thumbnail>
                  <urlsolve>https://streamcherry.com/embed/kokcbrbpoqmccfqt</urlsolve>	
				</subitem>
				
				<subitem>
                  <title>[COLOR green][B]480p[/B][/COLOR] [COLOR lightyellow][B]  vidoza.net[/B][/COLOR]</title>
			      <thumbnail>https://netbusinessrating.com/inc/imghttps.php?url=aHR0cHM6Ly9uZXRidXNpbmVzc3JhdGluZy5jb20vaW1nL3VwbG9hZGVkL3RodW1iL3RodW1iXzQyMDk1X3ZpZG96YV8xNzA3MzAwODUyNTkucG5n</thumbnail>
                  <urlsolve>https://vidoza.net/embed-fiaoyxktpyiz.html</urlsolve>	
				</subitem>
				
				<subitem>
                  <title>[COLOR green][B]480p[/B][/COLOR] [COLOR lightyellow][B]  vidoza.net[/B][/COLOR]</title>
			      <thumbnail>https://netbusinessrating.com/inc/imghttps.php?url=aHR0cHM6Ly9uZXRidXNpbmVzc3JhdGluZy5jb20vaW1nL3VwbG9hZGVkL3RodW1iL3RodW1iXzQyMDk1X3ZpZG96YV8xNzA3MzAwODUyNTkucG5n</thumbnail>
                  <urlsolve>https://vidoza.net/embed-1lkmbc1zf9ld.html</urlsolve>	
				</subitem>
				
				<subitem>
                  <title>[COLOR green][B]480p[/B][/COLOR] [COLOR lightyellow][B]  vidoza.net[/B][/COLOR]</title>
			      <thumbnail>https://netbusinessrating.com/inc/imghttps.php?url=aHR0cHM6Ly9uZXRidXNpbmVzc3JhdGluZy5jb20vaW1nL3VwbG9hZGVkL3RodW1iL3RodW1iXzQyMDk1X3ZpZG96YV8xNzA3MzAwODUyNTkucG5n</thumbnail>
                  <urlsolve>https://vidoza.net/embed-vnfx104dknkr.html</urlsolve>	
				</subitem>
				
				<subitem>
                  <title>[COLOR green][B]480p[/B][/COLOR] [COLOR lightyellow][B]  vidoza.net[/B][/COLOR]</title>
			      <thumbnail>https://netbusinessrating.com/inc/imghttps.php?url=aHR0cHM6Ly9uZXRidXNpbmVzc3JhdGluZy5jb20vaW1nL3VwbG9hZGVkL3RodW1iL3RodW1iXzQyMDk1X3ZpZG96YV8xNzA3MzAwODUyNTkucG5n</thumbnail>
                  <urlsolve>https://vidoza.net/embed-sqhx4fery42m.html</urlsolve>	
				</subitem>
				
				<subitem>
                  <title>[COLOR green][B]480p[/B][/COLOR] [COLOR lightyellow][B]  vidto.me[/B][/COLOR]</title>
			      <thumbnail>http://static.vidto.me/static/images/header-logo.png</thumbnail>
                  <urlsolve>http://vidto.me/embed-8f6amsgo2n4r-693x495.html</urlsolve>	
				</subitem>
			</subitems>
		</subchannel>	
<!-----------------------------------------------------------------END------------------------------------------------------------------------------------>	
        <subchannel>
          <name>[COLOR lime]•[/COLOR]    [COLOR yellow][B][s01e02][/B][/COLOR]     [COLOR lightyellow][B] Water[/B][/COLOR]</name>
          <thumbnail>https://upload.wikimedia.org/wikipedia/en/c/c6/BSG_Season_1_DVD.jpg</thumbnail>
          <fanart>https://www.walldevil.com/wallpapers/a46/battlestar-galactica-last-supper.jpg</fanart>
            <subitems>
                <subitem>
                  <title>[COLOR green][B]480p[/B][/COLOR] [COLOR lightyellow][B]  openload.co[/B][/COLOR]</title>
			      <thumbnail>https://openload.co/assets/img/logo.png</thumbnail>
                  <urlsolve>https://openload.co/embed/IUuUHTXbukU</urlsolve>	
				</subitem>
				
				<subitem>
                  <title>[COLOR green][B]480p[/B][/COLOR] [COLOR lightyellow][B]  openload.co[/B][/COLOR]</title>
			      <thumbnail>https://openload.co/assets/img/logo.png</thumbnail>
                  <urlsolve>https://openload.co/embed/j5ccDG9G8lw</urlsolve>	
				</subitem>
				
				<subitem>
                  <title>[COLOR green][B]480p[/B][/COLOR] [COLOR lightyellow][B]  openload.co[/B][/COLOR]</title>
			      <thumbnail>https://openload.co/assets/img/logo.png</thumbnail>
                  <urlsolve>https://openload.co/embed/AcMX3I8q-Wg</urlsolve>	
				</subitem>
				
				<subitem>
                  <title>[COLOR green][B]480p[/B][/COLOR] [COLOR lightyellow][B]  openload.co[/B][/COLOR]</title>
			      <thumbnail>https://openload.co/assets/img/logo.png</thumbnail>
                  <urlsolve>https://openload.co/embed/3173-3vqCQ0</urlsolve>	
				</subitem>
				
				<subitem>
                  <title>[COLOR green][B]480p[/B][/COLOR] [COLOR lightyellow][B]  streamango.com[/B][/COLOR]</title>
			      <thumbnail>https://streamango.com/assets/img/feature-icon3.png</thumbnail>
                  <urlsolve>http://streamango.com/embed/lofcbmprlkcfkflk</urlsolve>	
				</subitem>
				
				<subitem>
                  <title>[COLOR green][B]480p[/B][/COLOR] [COLOR lightyellow][B]  streamango.com[/B][/COLOR]</title>
			      <thumbnail>https://streamango.com/assets/img/feature-icon3.png</thumbnail>
                  <urlsolve>http://streamango.com/embed/pdssnfndtnosoltt</urlsolve>	
				</subitem>
				
				<subitem>
                  <title>[COLOR green][B]480p[/B][/COLOR] [COLOR lightyellow][B]  streamango.com[/B][/COLOR]</title>
			      <thumbnail>https://streamango.com/assets/img/feature-icon3.png</thumbnail>
                  <urlsolve>http://streamango.com/embed/ofblobmspcmeqcpb</urlsolve>	
				</subitem>
				
				<subitem>
                  <title>[COLOR green][B]480p[/B][/COLOR] [COLOR lightyellow][B]  streamango.com[/B][/COLOR]</title>
			      <thumbnail>https://streamango.com/assets/img/feature-icon3.png</thumbnail>
                  <urlsolve>http://streamango.com/embed/msadrsetktmtdepc</urlsolve>	
				</subitem>
				
				<subitem>
                  <title>[COLOR green][B]480p[/B][/COLOR] [COLOR lightyellow][B]  streamcherry.com[/B][/COLOR]</title>
			      <thumbnail>http://streamcherry.com/assets/img/logo.png</thumbnail>
                  <urlsolve>http://streamcherry.com/embed/qoabnqannalkbekm</urlsolve>	
				</subitem>
				
				<subitem>
                  <title>[COLOR green][B]480p[/B][/COLOR] [COLOR lightyellow][B]  streamcherry.com[/B][/COLOR]</title>
			      <thumbnail>http://streamcherry.com/assets/img/logo.png</thumbnail>
                  <urlsolve>http://streamcherry.com/embed/alrpdqbnprfaccre</urlsolve>	
				</subitem>
				
				<subitem>
                  <title>[COLOR green][B]480p[/B][/COLOR] [COLOR lightyellow][B]  streamcherry.com[/B][/COLOR]</title>
			      <thumbnail>http://streamcherry.com/assets/img/logo.png</thumbnail>
                  <urlsolve>http://streamcherry.com/embed/lpopmlepbanptqck</urlsolve>	
				</subitem>
				
				<subitem>
                  <title>[COLOR green][B]480p[/B][/COLOR] [COLOR lightyellow][B]  streamcherry.com[/B][/COLOR]</title>
			      <thumbnail>http://streamcherry.com/assets/img/logo.png</thumbnail>
                  <urlsolve>http://streamcherry.com/embed/eqnnstepopaobqsm</urlsolve>	
				</subitem>
				
				<subitem>
                  <title>[COLOR green][B]480p[/B][/COLOR] [COLOR lightyellow][B]  vidoza.net[/B][/COLOR]</title>
			      <thumbnail>https://netbusinessrating.com/inc/imghttps.php?url=aHR0cHM6Ly9uZXRidXNpbmVzc3JhdGluZy5jb20vaW1nL3VwbG9hZGVkL3RodW1iL3RodW1iXzQyMDk1X3ZpZG96YV8xNzA3MzAwODUyNTkucG5n</thumbnail>
                  <urlsolve>https://vidoza.net/embed-1ulatiip6o10.html</urlsolve>	
				</subitem>
				
				<subitem>
                  <title>[COLOR green][B]480p[/B][/COLOR] [COLOR lightyellow][B]  vidoza.net[/B][/COLOR]</title>
			      <thumbnail>https://netbusinessrating.com/inc/imghttps.php?url=aHR0cHM6Ly9uZXRidXNpbmVzc3JhdGluZy5jb20vaW1nL3VwbG9hZGVkL3RodW1iL3RodW1iXzQyMDk1X3ZpZG96YV8xNzA3MzAwODUyNTkucG5n</thumbnail>
                  <urlsolve>https://vidoza.net/embed-4d1w71rosyuk.html</urlsolve>	
				</subitem>
				
				<subitem>
                  <title>[COLOR green][B]480p[/B][/COLOR] [COLOR lightyellow][B]  vidoza.net[/B][/COLOR]</title>
			      <thumbnail>https://netbusinessrating.com/inc/imghttps.php?url=aHR0cHM6Ly9uZXRidXNpbmVzc3JhdGluZy5jb20vaW1nL3VwbG9hZGVkL3RodW1iL3RodW1iXzQyMDk1X3ZpZG96YV8xNzA3MzAwODUyNTkucG5n</thumbnail>
                  <urlsolve>https://vidoza.net/embed-8n06rnz2tl7w.html</urlsolve>	
				</subitem>
				
				<subitem>
                  <title>[COLOR green][B]480p[/B][/COLOR] [COLOR lightyellow][B]  vidoza.net[/B][/COLOR]</title>
			      <thumbnail>https://netbusinessrating.com/inc/imghttps.php?url=aHR0cHM6Ly9uZXRidXNpbmVzc3JhdGluZy5jb20vaW1nL3VwbG9hZGVkL3RodW1iL3RodW1iXzQyMDk1X3ZpZG96YV8xNzA3MzAwODUyNTkucG5n</thumbnail>
                  <urlsolve>https://vidoza.net/embed-pwnq3pargiv4.html</urlsolve>	
				</subitem>
				
				<subitem>
                  <title>[COLOR green][B]480p[/B][/COLOR] [COLOR lightyellow][B]  vidto.me[/B][/COLOR]</title>
			      <thumbnail>http://static.vidto.me/static/images/header-logo.png</thumbnail>
                  <urlsolve>http://vidto.me/embed-hbh0eaauj8ug-693x495.html</urlsolve>	
				</subitem>
			</subitems>
		</subchannel>		
<!-----------------------------------------------------------------END------------------------------------------------------------------------------------>	
        <subchannel>
          <name>[COLOR lime]•[/COLOR]    [COLOR yellow][B][s01e03][/B][/COLOR]     [COLOR lightyellow][B] Bastille Day[/B][/COLOR]</name>
          <thumbnail>https://upload.wikimedia.org/wikipedia/en/c/c6/BSG_Season_1_DVD.jpg</thumbnail>
          <fanart>https://www.walldevil.com/wallpapers/a46/battlestar-galactica-last-supper.jpg</fanart>
            <subitems>
                <subitem>
                  <title>[COLOR green][B]480p[/B][/COLOR] [COLOR lightyellow][B]  openload.co[/B][/COLOR]</title>
			      <thumbnail>https://openload.co/assets/img/logo.png</thumbnail>
                  <urlsolve>https://openload.co/embed/t03XN6auqpM</urlsolve>	
				</subitem>
				
				<subitem>
                  <title>[COLOR green][B]480p[/B][/COLOR] [COLOR lightyellow][B]  openload.co[/B][/COLOR]</title>
			      <thumbnail>https://openload.co/assets/img/logo.png</thumbnail>
                  <urlsolve>https://openload.co/embed/EqLvoP_9jYw</urlsolve>	
				</subitem>
				
				<subitem>
                  <title>[COLOR green][B]480p[/B][/COLOR] [COLOR lightyellow][B]  openload.co[/B][/COLOR]</title>
			      <thumbnail>https://openload.co/assets/img/logo.png</thumbnail>
                  <urlsolve>https://openload.co/embed/2qLYE_DJBxQ</urlsolve>	
				</subitem>
				
				<subitem>
                  <title>[COLOR green][B]480p[/B][/COLOR] [COLOR lightyellow][B]  openload.co[/B][/COLOR]</title>
			      <thumbnail>https://openload.co/assets/img/logo.png</thumbnail>
                  <urlsolve>https://openload.co/embed/iN9RSrnaEtY</urlsolve>	
				</subitem>
				
				<subitem>
                  <title>[COLOR green][B]480p[/B][/COLOR] [COLOR lightyellow][B]  streamango.com[/B][/COLOR]</title>
			      <thumbnail>https://streamango.com/assets/img/feature-icon3.png</thumbnail>
                  <urlsolve>http://streamango.com/embed/ttrftrtqabtctcqn</urlsolve>	
				</subitem>
				
				<subitem>
                  <title>[COLOR green][B]480p[/B][/COLOR] [COLOR lightyellow][B]  streamango.com[/B][/COLOR]</title>
			      <thumbnail>https://streamango.com/assets/img/feature-icon3.png</thumbnail>
                  <urlsolve>http://streamango.com/embed/plmaafqnlfnbonfl</urlsolve>	
				</subitem>
				
				<subitem>
                  <title>[COLOR green][B]480p[/B][/COLOR] [COLOR lightyellow][B]  streamango.com[/B][/COLOR]</title>
			      <thumbnail>https://streamango.com/assets/img/feature-icon3.png</thumbnail>
                  <urlsolve>http://streamango.com/embed/dtblrlmbaacfattq</urlsolve>	
				</subitem>
				
				<subitem>
                  <title>[COLOR green][B]480p[/B][/COLOR] [COLOR lightyellow][B]  streamango.com[/B][/COLOR]</title>
			      <thumbnail>https://streamango.com/assets/img/feature-icon3.png</thumbnail>
                  <urlsolve>http://streamango.com/embed/coffslabestpstrn</urlsolve>	
				</subitem>
				
				<subitem>
                  <title>[COLOR green][B]480p[/B][/COLOR] [COLOR lightyellow][B]  streamcherry.com[/B][/COLOR]</title>
			      <thumbnail>http://streamcherry.com/assets/img/logo.png</thumbnail>
                  <urlsolve>http://streamcherry.com/embed/lescnapqsdrqdqcq</urlsolve>	
				</subitem>
				
				<subitem>
                  <title>[COLOR green][B]480p[/B][/COLOR] [COLOR lightyellow][B]  streamcherry.com[/B][/COLOR]</title>
			      <thumbnail>http://streamcherry.com/assets/img/logo.png</thumbnail>
                  <urlsolve>http://streamcherry.com/embed/kokofqbeltcqneds</urlsolve>	
				</subitem>
				
				<subitem>
                  <title>[COLOR green][B]480p[/B][/COLOR] [COLOR lightyellow][B]  streamcherry.com[/B][/COLOR]</title>
			      <thumbnail>http://streamcherry.com/assets/img/logo.png</thumbnail>
                  <urlsolve>http://streamcherry.com/embed/ceqrtookcqdnmaqq</urlsolve>	
				</subitem>
				
				<subitem>
                  <title>[COLOR green][B]480p[/B][/COLOR] [COLOR lightyellow][B]  streamcherry.com[/B][/COLOR]</title>
			      <thumbnail>http://streamcherry.com/assets/img/logo.png</thumbnail>
                  <urlsolve>http://streamcherry.com/embed/kfnpdklkmsdrslll</urlsolve>	
				</subitem>
				
				<subitem>
                  <title>[COLOR green][B]480p[/B][/COLOR] [COLOR lightyellow][B]  vidoza.net[/B][/COLOR]</title>
			      <thumbnail>https://netbusinessrating.com/inc/imghttps.php?url=aHR0cHM6Ly9uZXRidXNpbmVzc3JhdGluZy5jb20vaW1nL3VwbG9hZGVkL3RodW1iL3RodW1iXzQyMDk1X3ZpZG96YV8xNzA3MzAwODUyNTkucG5n</thumbnail>
                  <urlsolve>https://vidoza.net/embed-av3u1y0nylt5.html</urlsolve>	
				</subitem>
				
				<subitem>
                  <title>[COLOR green][B]480p[/B][/COLOR] [COLOR lightyellow][B]  vidoza.net[/B][/COLOR]</title>
			      <thumbnail>https://netbusinessrating.com/inc/imghttps.php?url=aHR0cHM6Ly9uZXRidXNpbmVzc3JhdGluZy5jb20vaW1nL3VwbG9hZGVkL3RodW1iL3RodW1iXzQyMDk1X3ZpZG96YV8xNzA3MzAwODUyNTkucG5n</thumbnail>
                  <urlsolve>https://vidoza.net/embed-wekmtg7g4n58.html</urlsolve>	
				</subitem>
				
				<subitem>
                  <title>[COLOR green][B]480p[/B][/COLOR] [COLOR lightyellow][B]  vidoza.net[/B][/COLOR]</title>
			      <thumbnail>https://netbusinessrating.com/inc/imghttps.php?url=aHR0cHM6Ly9uZXRidXNpbmVzc3JhdGluZy5jb20vaW1nL3VwbG9hZGVkL3RodW1iL3RodW1iXzQyMDk1X3ZpZG96YV8xNzA3MzAwODUyNTkucG5n</thumbnail>
                  <urlsolve>https://vidoza.net/embed-9yvfnkwmp9c9.html</urlsolve>	
				</subitem>
				
				<subitem>
                  <title>[COLOR green][B]480p[/B][/COLOR] [COLOR lightyellow][B]  vidoza.net[/B][/COLOR]</title>
			      <thumbnail>https://netbusinessrating.com/inc/imghttps.php?url=aHR0cHM6Ly9uZXRidXNpbmVzc3JhdGluZy5jb20vaW1nL3VwbG9hZGVkL3RodW1iL3RodW1iXzQyMDk1X3ZpZG96YV8xNzA3MzAwODUyNTkucG5n</thumbnail>
                  <urlsolve>https://vidoza.net/embed-e7ug47nvvnjs.html</urlsolve>	
				</subitem>
				
				<subitem>
                  <title>[COLOR green][B]480p[/B][/COLOR] [COLOR lightyellow][B]  vidto.me[/B][/COLOR]</title>
			      <thumbnail>http://static.vidto.me/static/images/header-logo.png</thumbnail>
                  <urlsolve>http://vidto.me/embed-xo6j33fu617v-693x495.html</urlsolve>	
				</subitem>
			</subitems>
		</subchannel>	
<!-----------------------------------------------------------------END------------------------------------------------------------------------------------>	
        <subchannel>
          <name>[COLOR lime]•[/COLOR]    [COLOR yellow][B][s01e04][/B][/COLOR]     [COLOR lightyellow][B] Act of Contrition[/B][/COLOR]</name>
          <thumbnail>https://upload.wikimedia.org/wikipedia/en/c/c6/BSG_Season_1_DVD.jpg</thumbnail>
          <fanart>https://www.walldevil.com/wallpapers/a46/battlestar-galactica-last-supper.jpg</fanart>
            <subitems>
                <subitem>
                  <title>[COLOR green][B]480p[/B][/COLOR] [COLOR lightyellow][B]  freedisc.pl[/B][/COLOR]</title>
			      <thumbnail>https://freedisc.pl/streaming/logo.png?i=0</thumbnail>
                  <link>https://stream.freedisc.pl/video/9902631/battlestar-galactica-s01e04-dvdrip-lektor-pl.mp4</link>	
				</subitem>
			</subitems>
		</subchannel>	
<!-----------------------------------------------------------------END------------------------------------------------------------------------------------>	
        <subchannel>
          <name>[COLOR lime]•[/COLOR]    [COLOR yellow][B][s01e05][/B][/COLOR]     [COLOR lightyellow][B] You Can't Go Home Again[/B][/COLOR]</name>
          <thumbnail>https://upload.wikimedia.org/wikipedia/en/c/c6/BSG_Season_1_DVD.jpg</thumbnail>
          <fanart>https://www.walldevil.com/wallpapers/a46/battlestar-galactica-last-supper.jpg</fanart>
            <subitems>
                <subitem>
                  <title>[COLOR green][B]480p[/B][/COLOR] [COLOR lightyellow][B]  freedisc.pl[/B][/COLOR]</title>
			      <thumbnail>https://freedisc.pl/streaming/logo.png?i=0</thumbnail>
                  <link>https://stream.freedisc.pl/video/9902893/battlestar-galactica-s01e05-dvdrip-lektor-pl.mp4</link>	
				</subitem>
			</subitems>
		</subchannel>
<!-----------------------------------------------------------------END------------------------------------------------------------------------------------>	
        <subchannel>
          <name>[COLOR lime]•[/COLOR]    [COLOR yellow][B][s01e06][/B][/COLOR]     [COLOR lightyellow][B] Litmus[/B][/COLOR]</name>
          <thumbnail>https://upload.wikimedia.org/wikipedia/en/c/c6/BSG_Season_1_DVD.jpg</thumbnail>
          <fanart>https://www.walldevil.com/wallpapers/a46/battlestar-galactica-last-supper.jpg</fanart>
            <subitems>
                <subitem>
                  <title>[COLOR green][B]480p[/B][/COLOR] [COLOR lightyellow][B]  freedisc.pl[/B][/COLOR]</title>
			      <thumbnail>https://freedisc.pl/streaming/logo.png?i=0</thumbnail>
                  <link>https://stream.freedisc.pl/video/9910887/battlestar-galactica-s01e06-dvdrip-lektor-pl.mp4</link>	
				</subitem>
			</subitems>
		</subchannel>
<!-----------------------------------------------------------------END------------------------------------------------------------------------------------>	
        <subchannel>
          <name>[COLOR lime]•[/COLOR]    [COLOR yellow][B][s01e07][/B][/COLOR]     [COLOR lightyellow][B] Six Degrees Of Separation[/B][/COLOR]</name>
          <thumbnail>https://upload.wikimedia.org/wikipedia/en/c/c6/BSG_Season_1_DVD.jpg</thumbnail>
          <fanart>https://www.walldevil.com/wallpapers/a46/battlestar-galactica-last-supper.jpg</fanart>
            <subitems>
                <subitem>
                  <title>[COLOR green][B]480p[/B][/COLOR] [COLOR lightyellow][B]  freedisc.pl[/B][/COLOR]</title>
			      <thumbnail>https://freedisc.pl/streaming/logo.png?i=0</thumbnail>
                  <link>https://stream.freedisc.pl/video/9910816/battlestar-galactica-s01e07-dvdrip-lektor-pl.mp4</link>	
				</subitem>
			</subitems>
		</subchannel>
<!-----------------------------------------------------------------END------------------------------------------------------------------------------------>	
        <subchannel>
          <name>[COLOR lime]•[/COLOR]    [COLOR yellow][B][s01e08][/B][/COLOR]     [COLOR lightyellow][B] Flesh And Bone[/B][/COLOR]</name>
          <thumbnail>https://upload.wikimedia.org/wikipedia/en/c/c6/BSG_Season_1_DVD.jpg</thumbnail>
          <fanart>https://www.walldevil.com/wallpapers/a46/battlestar-galactica-last-supper.jpg</fanart>
            <subitems>
                <subitem>
                  <title>[COLOR green][B]480p[/B][/COLOR] [COLOR lightyellow][B]  freedisc.pl[/B][/COLOR]</title>
			      <thumbnail>https://freedisc.pl/streaming/logo.png?i=0</thumbnail>
                  <link>https://stream.freedisc.pl/video/9910793/battlestar-galactica-s01e08-dvdrip-lektor-pl.mp4</link>	
				</subitem>
			</subitems>
		</subchannel>
<!-----------------------------------------------------------------END------------------------------------------------------------------------------------>	
        <subchannel>
          <name>[COLOR lime]•[/COLOR]    [COLOR yellow][B][s01e09][/B][/COLOR]     [COLOR lightyellow][B] Tigh Me Up, Tigh Me Down[/B][/COLOR]</name>
          <thumbnail>https://upload.wikimedia.org/wikipedia/en/c/c6/BSG_Season_1_DVD.jpg</thumbnail>
          <fanart>https://www.walldevil.com/wallpapers/a46/battlestar-galactica-last-supper.jpg</fanart>
            <subitems>
                <subitem>
                  <title>[COLOR green][B]480p[/B][/COLOR] [COLOR lightyellow][B]  freedisc.pl[/B][/COLOR]</title>
			      <thumbnail>https://freedisc.pl/streaming/logo.png?i=0</thumbnail>
                  <link>https://stream.freedisc.pl/video/9910862/battlestar-galactica-s01e09-dvdrip-lektor-pl.mp4</link>	
				</subitem>
			</subitems>
		</subchannel>
<!-----------------------------------------------------------------END------------------------------------------------------------------------------------>	
        <subchannel>
          <name>[COLOR lime]•[/COLOR]    [COLOR yellow][B][s01e10][/B][/COLOR]     [COLOR lightyellow][B] The Hand Of God[/B][/COLOR]</name>
          <thumbnail>https://upload.wikimedia.org/wikipedia/en/c/c6/BSG_Season_1_DVD.jpg</thumbnail>
          <fanart>https://www.walldevil.com/wallpapers/a46/battlestar-galactica-last-supper.jpg</fanart>
            <subitems>
                <subitem>
                  <title>[COLOR green][B]480p[/B][/COLOR] [COLOR lightyellow][B]  freedisc.pl[/B][/COLOR]</title>
			      <thumbnail>https://freedisc.pl/streaming/logo.png?i=0</thumbnail>
                  <link>https://stream.freedisc.pl/video/9925977/battlestar-galactica-s01e10-dvdrip-lektor-pl.mp4</link>	
				</subitem>
			</subitems>
		</subchannel>	
<!-----------------------------------------------------------------END------------------------------------------------------------------------------------>	
        <subchannel>
          <name>[COLOR lime]•[/COLOR]    [COLOR yellow][B][s01e11][/B][/COLOR]     [COLOR lightyellow][B] Colonial Day[/B][/COLOR]</name>
          <thumbnail>https://upload.wikimedia.org/wikipedia/en/c/c6/BSG_Season_1_DVD.jpg</thumbnail>
          <fanart>https://www.walldevil.com/wallpapers/a46/battlestar-galactica-last-supper.jpg</fanart>
            <subitems>
                <subitem>
                  <title>[COLOR green][B]480p[/B][/COLOR] [COLOR lightyellow][B]  freedisc.pl[/B][/COLOR]</title>
			      <thumbnail>https://freedisc.pl/streaming/logo.png?i=0</thumbnail>
                  <link>https://stream.freedisc.pl/video/9925976/battlestar-galactica-s01e11-dvdrip-lektor-pl.mp4</link>	
				</subitem>
			</subitems>
		</subchannel>	
<!-----------------------------------------------------------------END------------------------------------------------------------------------------------>	
        <subchannel>
          <name>[COLOR lime]•[/COLOR]    [COLOR yellow][B][s01e12][/B][/COLOR]     [COLOR lightyellow][B] Kobol's Last Gleaming – Part 1[/B][/COLOR]</name>
          <thumbnail>https://upload.wikimedia.org/wikipedia/en/c/c6/BSG_Season_1_DVD.jpg</thumbnail>
          <fanart>https://www.walldevil.com/wallpapers/a46/battlestar-galactica-last-supper.jpg</fanart>
            <subitems>
                <subitem>
                  <title>[COLOR green][B]480p[/B][/COLOR] [COLOR lightyellow][B]  freedisc.pl[/B][/COLOR]</title>
			      <thumbnail>https://freedisc.pl/streaming/logo.png?i=0</thumbnail>
                  <link>https://stream.freedisc.pl/video/9926019/battlestar-galactica-s01e12-dvdrip-lektor-pl.mp4</link>	
				</subitem>
			</subitems>
		</subchannel>	
<!-----------------------------------------------------------------END------------------------------------------------------------------------------------>	
        <subchannel>
          <name>[COLOR lime]•[/COLOR]    [COLOR yellow][B][s01e13][/B][/COLOR]     [COLOR lightyellow][B] Kobol's Last Gleaming – Part 2[/B][/COLOR]</name>
          <thumbnail>https://upload.wikimedia.org/wikipedia/en/c/c6/BSG_Season_1_DVD.jpg</thumbnail>
          <fanart>https://www.walldevil.com/wallpapers/a46/battlestar-galactica-last-supper.jpg</fanart>
            <subitems>
                <subitem>
                  <title>[COLOR green][B]480p[/B][/COLOR] [COLOR lightyellow][B]  freedisc.pl[/B][/COLOR]</title>
			      <thumbnail>https://freedisc.pl/streaming/logo.png?i=0</thumbnail>
                  <link>https://stream.freedisc.pl/video/9925992/battlestar-galactica-s01e13-dvdrip-lektor-pl.mp4</link>	
				</subitem>
			</subitems>
		</subchannel>			
	</channel>	
</channels>		  